retype/__init__.py
retype/__main__.py
retype/config.py
retype/retype_hgext.py
retype/version.py
retype-22.8.0.dist-info/LICENSE
retype-22.8.0.dist-info/METADATA
retype-22.8.0.dist-info/WHEEL
retype-22.8.0.dist-info/entry_points.txt
retype-22.8.0.dist-info/top_level.txt
retype-22.8.0.dist-info/RECORD
