Metadata-Version: 2.1
Name: retype
Version: 22.8.0
Summary: re-apply types from .pyi stub files to your codebase
Home-page: https://github.com/ambv/retype
Author-email: lukasz@langa.pl
License: MIT
Project-URL: Source, https://github.com/ambv/retype
Project-URL: Tracker, https://github.com/ambv/retype/issues
Keywords: mypy typing typehints type hints pep484 pyi stubs
Platform: any
Classifier: Development Status :: 4 - Beta
Classifier: Environment :: Console
Classifier: Intended Audience :: Developers
Classifier: License :: OSI Approved :: MIT License
Classifier: Operating System :: OS Independent
Classifier: Programming Language :: Python
Classifier: Programming Language :: Python :: 3
Classifier: Programming Language :: Python :: 3 :: Only
Classifier: Programming Language :: Python :: 3.7
Classifier: Programming Language :: Python :: 3.8
Classifier: Programming Language :: Python :: 3.9
Classifier: Programming Language :: Python :: 3.10
Classifier: Topic :: Software Development :: Libraries :: Python Modules
Classifier: Topic :: Software Development :: Quality Assurance
Requires-Python: >=3.7
License-File: LICENSE
Requires-Dist: click (>=7)
Requires-Dist: pathspec (<1,>=0.5.9)
Requires-Dist: typed-ast (>=1.3)
Provides-Extra: test
Requires-Dist: covdefaults (>=2) ; extra == 'test'
Requires-Dist: pytest (>=6) ; extra == 'test'
Requires-Dist: pytest-cov (>=3) ; extra == 'test'
